MANIFEST.in
README.rst
setup.py
src/digimat/__init__.py
src/digimat.mbio.egg-info/PKG-INFO
src/digimat.mbio.egg-info/SOURCES.txt
src/digimat.mbio.egg-info/dependency_links.txt
src/digimat.mbio.egg-info/namespace_packages.txt
src/digimat.mbio.egg-info/not-zip-safe
src/digimat.mbio.egg-info/requires.txt
src/digimat.mbio.egg-info/top_level.txt
src/digimat/mbio/__init__.py
src/digimat/mbio/belimo.py
src/digimat/mbio/binarypayload.py
src/digimat/mbio/config.py
src/digimat/mbio/danfossally.py
src/digimat/mbio/device.py
src/digimat/mbio/digimatsmartio.py
src/digimat/mbio/easybus.py
src/digimat/mbio/ebm.py
src/digimat/mbio/gateway.py
src/digimat/mbio/gsheet.py
src/digimat/mbio/hue.py
src/digimat/mbio/isma.py
src/digimat/mbio/items.py
src/digimat/mbio/knx.py
src/digimat/mbio/linknotifier.py
src/digimat/mbio/mbio.py
src/digimat/mbio/mbiosocket.py
src/digimat/mbio/meteosuisse.py
src/digimat/mbio/metzconnect.py
src/digimat/mbio/mpbus-protocol.py
src/digimat/mbio/mystrom.py
src/digimat/mbio/netscan.py
src/digimat/mbio/networktopology.py
src/digimat/mbio/pinger.py
src/digimat/mbio/scanner.py
src/digimat/mbio/scheduler.py
src/digimat/mbio/sensorpush.py
src/digimat/mbio/sensortec.py
src/digimat/mbio/shelly.py
src/digimat/mbio/task.py
src/digimat/mbio/tasktest.py
src/digimat/mbio/value.py
src/digimat/mbio/valuenotifier.py
src/digimat/mbio/vio.py
src/digimat/mbio/vplc.py
src/digimat/mbio/ws-script-zoneeditor.js
src/digimat/mbio/ws-zoneeditor.html
src/digimat/mbio/wserver.py
src/digimat/mbio/wsmonitor.py
src/digimat/mbio/xknxclient.py
src/digimat/mbio/xmlconfig.py