Metadata-Version: 2.4
Name: digimat.mbio
Version: 0.2.23
Summary: Digimat MBIO System
Home-page: https://github.com/digimat/digimat-mbio
Author: Frederic Hess
Author-email: fhess@st-sa.ch
License: PSF
Classifier: Development Status :: 4 - Beta
Classifier: Programming Language :: Python :: 3
Requires-Dist: importlib-resources
Requires-Dist: digimat.lp
Requires-Dist: digimat.units
Requires-Dist: digimat.danfossally
Requires-Dist: ptable
Requires-Dist: rich
Requires-Dist: pymodbus==3.7.2
Requires-Dist: requests
Requires-Dist: httpx
Requires-Dist: openpyxl
Requires-Dist: ipcalc
Requires-Dist: gspread
Requires-Dist: packaging
Requires-Dist: setuptools
Dynamic: author
Dynamic: author-email
Dynamic: classifier
Dynamic: description
Dynamic: home-page
Dynamic: license
Dynamic: requires-dist
Dynamic: summary
